typing_inspect_isle/__init__.py
typing_inspect_isle/_typing_inspect.py
typing_inspect_isle/_version.py
typing_inspect_isle-0.2.0.dist-info/LICENSE
typing_inspect_isle-0.2.0.dist-info/METADATA
typing_inspect_isle-0.2.0.dist-info/WHEEL
typing_inspect_isle-0.2.0.dist-info/top_level.txt
typing_inspect_isle-0.2.0.dist-info/RECORD
